<?xml version="1.0" encoding="UTF-8"?>
<gresources>
  <gresource prefix="/org/gnome/Chess/ui">
    <file preprocess="xml-stripblanks">gnome-chess.ui</file>
    <file preprocess="xml-stripblanks">preferences.ui</file>
    <file preprocess="xml-stripblanks">promotion-type-selector.ui</file>
  </gresource>
  <gresource prefix="/org/gnome/Chess/pieces">
    <file preprocess="xml-stripblanks" alias="fancy/blackBishop.svg">pieces/fancy/blackBishop.svg</file>
    <file preprocess="xml-stripblanks" alias="fancy/blackKing.svg">pieces/fancy/blackKing.svg</file>
    <file preprocess="xml-stripblanks" alias="fancy/blackKnight.svg">pieces/fancy/blackKnight.svg</file>
    <file preprocess="xml-stripblanks" alias="fancy/blackPawn.svg">pieces/fancy/blackPawn.svg</file>
    <file preprocess="xml-stripblanks" alias="fancy/blackQueen.svg">pieces/fancy/blackQueen.svg</file>
    <file preprocess="xml-stripblanks" alias="fancy/blackRook.svg">pieces/fancy/blackRook.svg</file>
    <file preprocess="xml-stripblanks" alias="fancy/whiteBishop.svg">pieces/fancy/whiteBishop.svg</file>
    <file preprocess="xml-stripblanks" alias="fancy/whiteKing.svg">pieces/fancy/whiteKing.svg</file>
    <file preprocess="xml-stripblanks" alias="fancy/whiteKnight.svg">pieces/fancy/whiteKnight.svg</file>
    <file preprocess="xml-stripblanks" alias="fancy/whitePawn.svg">pieces/fancy/whitePawn.svg</file>
    <file preprocess="xml-stripblanks" alias="fancy/whiteQueen.svg">pieces/fancy/whiteQueen.svg</file>
    <file preprocess="xml-stripblanks" alias="fancy/whiteRook.svg">pieces/fancy/whiteRook.svg</file>
    <file preprocess="xml-stripblanks" alias="simple/blackBishop.svg">pieces/simple/blackBishop.svg</file>
    <file preprocess="xml-stripblanks" alias="simple/blackKing.svg">pieces/simple/blackKing.svg</file>
    <file preprocess="xml-stripblanks" alias="simple/blackKnight.svg">pieces/simple/blackKnight.svg</file>
    <file preprocess="xml-stripblanks" alias="simple/blackPawn.svg">pieces/simple/blackPawn.svg</file>
    <file preprocess="xml-stripblanks" alias="simple/blackQueen.svg">pieces/simple/blackQueen.svg</file>
    <file preprocess="xml-stripblanks" alias="simple/blackRook.svg">pieces/simple/blackRook.svg</file>
    <file preprocess="xml-stripblanks" alias="simple/whiteBishop.svg">pieces/simple/whiteBishop.svg</file>
    <file preprocess="xml-stripblanks" alias="simple/whiteKing.svg">pieces/simple/whiteKing.svg</file>
    <file preprocess="xml-stripblanks" alias="simple/whiteKnight.svg">pieces/simple/whiteKnight.svg</file>
    <file preprocess="xml-stripblanks" alias="simple/whitePawn.svg">pieces/simple/whitePawn.svg</file>
    <file preprocess="xml-stripblanks" alias="simple/whiteQueen.svg">pieces/simple/whiteQueen.svg</file>
    <file preprocess="xml-stripblanks" alias="simple/whiteRook.svg">pieces/simple/whiteRook.svg</file>
  </gresource>
  <gresource prefix="/org/gnome/Chess/gtk">
    <file preprocess="xml-stripblanks">help-overlay.ui</file>
  </gresource>
</gresources>
